loopex/__init__.py
loopex/do_while.py
loopex-0.0.1.dist-info/METADATA
loopex-0.0.1.dist-info/WHEEL
loopex-0.0.1.dist-info/licenses/LICENSE
loopex-0.0.1.dist-info/RECORD
