Metadata-Version: 2.3
Name: LoopEx
Version: 0.0.1
Summary: A extension enhancing Python loop.
Project-URL: Homepage, https://github.com/glyzinieh/python-loop-extension
Project-URL: Issues, https://github.com/glyzinieh/python-loop-extension/issues
Author-email: glyzinieh <wisteriatp@gmail.com>
License-File: LICENSE
Requires-Python: >=3.0
